orchestra_llm/__init__.py
orchestra_llm/callbacks/argilla.py
orchestra_llm/core/composer.py
orchestra_llm/core/orchestrator.py
orchestra_llm/core/schema.py
orchestra_llm/prompt/__init__.py
orchestra_llm/prompt/prompt.py
orchestra_llm/retriever/model.py
orchestra_llm/retriever/qdrant.py
orchestra_llm/router/__init__.py
orchestra_llm/router/router.py
orchestra_llm-0.1.0.dist-info/METADATA
orchestra_llm-0.1.0.dist-info/WHEEL
orchestra_llm-0.1.0.dist-info/RECORD
